odoo/addons/account_move_line_due_date/README.rst
odoo/addons/account_move_line_due_date/__init__.py
odoo/addons/account_move_line_due_date/__manifest__.py
odoo/addons/account_move_line_due_date/static/description/icon.png
odoo/addons/account_move_line_due_date/views/account_move_views.xml
odoo13_addon_account_move_line_due_date-13.0.1.0.0.dist-info/METADATA
odoo13_addon_account_move_line_due_date-13.0.1.0.0.dist-info/WHEEL
odoo13_addon_account_move_line_due_date-13.0.1.0.0.dist-info/top_level.txt
odoo13_addon_account_move_line_due_date-13.0.1.0.0.dist-info/RECORD
